prolysis/__init__.py
prolysis/analysis/EMD_based_framework.py
prolysis/analysis/Optimzation_Goals.py
prolysis/analysis/__init__.py
prolysis/analysis/dfg_functions.py
prolysis/analysis/evaluation.py
prolysis/analysis/explainability_extraction.py
prolysis/analysis/python_emsc/__init__.py
prolysis/analysis/python_emsc/emsc.py
prolysis/analysis/python_emsc/stochastic.py
prolysis/analysis/python_emsc/util.py
prolysis/calls/__init__.py
prolysis/calls/minerful_calls.py
prolysis/discovery/__init__.py
prolysis/discovery/discovery.py
prolysis/discovery/subtree_plain.py
prolysis/discovery/base_case/__init__.py
prolysis/discovery/base_case/check.py
prolysis/discovery/candidate_search/__init__.py
prolysis/discovery/candidate_search/is_allowed.py
prolysis/discovery/candidate_search/is_allowed_2 - Copy.py
prolysis/discovery/candidate_search/is_allowed_2.py
prolysis/discovery/candidate_search/is_allowed_single.py
prolysis/discovery/candidate_search/search - Copy.py
prolysis/discovery/candidate_search/search.py
prolysis/discovery/cut_quality/__init__.py
prolysis/discovery/cut_quality/cost_functions/__init__.py
prolysis/discovery/cut_quality/cost_functions/cost_functions.py
prolysis/discovery/split_functions/__init__.py
prolysis/discovery/split_functions/split.py
prolysis/rules_handling/__init__.py
prolysis/rules_handling/declare_processing.py
prolysis/rules_handling/utils.py
prolysis/util/__init__.py
prolysis/util/functions.py
prolysis/util/logging.py
prolysis/util/redis_connection.py
prolysis/util/utils.py
prolysis/util/dfg/__init__.py
prolysis/util/dfg/algorithm.py
prolysis/util/dfg/parameters.py
prolysis/util/dfg/replacement.py
prolysis/util/dfg/adapters/__init__.py
prolysis/util/dfg/adapters/pandas/__init__.py
prolysis/util/dfg/adapters/pandas/df_statistics.py
prolysis/util/dfg/adapters/pandas/freq_triples.py
prolysis/util/dfg/utils/__init__.py
prolysis/util/dfg/utils/dfg_utils.py
prolysis/util/dfg/variants/__init__.py
prolysis/util/dfg/variants/case_attributes.py
prolysis-0.2.1.dist-info/LICENSE
prolysis-0.2.1.dist-info/METADATA
prolysis-0.2.1.dist-info/WHEEL
prolysis-0.2.1.dist-info/top_level.txt
prolysis-0.2.1.dist-info/RECORD
